{
	"name": "ds_sql_gold_dim_paquete",
	"properties": {
		"linkedServiceName": {
			"referenceName": "ls_sql_dw_subsidio",
			"type": "LinkedServiceReference"
		},
		"annotations": [],
		"type": "AzureSqlTable",
		"schema": [
			{
				"name": "paquete_key",
				"type": "int",
				"precision": 10
			},
			{
				"name": "paquete_id",
				"type": "int",
				"precision": 10
			},
			{
				"name": "nombre",
				"type": "varchar"
			},
			{
				"name": "contenido",
				"type": "varchar"
			},
			{
				"name": "peso_estandar_kg",
				"type": "decimal",
				"precision": 6,
				"scale": 2
			},
			{
				"name": "costo_estimado_bs",
				"type": "decimal",
				"precision": 10,
				"scale": 2
			}
		],
		"typeProperties": {
			"schema": "gold",
			"table": "dim_paquete"
		}
	}
}